{
    "Monday 01st Dec 2025 - Schedule Time UK GMT": {
        "TV Shows": [
            {
                "time": "20:00",
                "event": "The Kelly Clarkson Show Season 7, Episode 44",
                "channels": [
                    {
                        "channel_name": "NBCNY USA",
                        "channel_id": "769"
                    }
                ]
            },
            {
                "time": "20:00",
                "event": "General Hospital Season 63, Episode 56",
                "channels": [
                    {
                        "channel_name": "ABC NY USA",
                        "channel_id": "766"
                    }
                ]
            },
            {
                "time": "23:00",
                "event": "Monday Night Countdown Live",
                "channels": [
                    {
                        "channel_name": "ESPN USA",
                        "channel_id": "44"
                    }
                ]
            },
            {
                "time": "00:00",
                "event": "La isla: Desaf\u00edo extremo Season 2, Episode 46 \u2022 Finale",
                "channels": [
                    {
                        "channel_name": "NBC Universo",
                        "channel_id": "845"
                    },
                    {
                        "channel_name": "Telemundo USA",
                        "channel_id": "131"
                    }
                ]
            },
            {
                "time": "00:00",
                "event": "Jeopardy! Season 42, Episode 61",
                "channels": [
                    {
                        "channel_name": "ABC NY USA",
                        "channel_id": "766"
                    }
                ]
            },
            {
                "time": "00:00",
                "event": "2026 Athletes Unlimited Softball League Draft Live",
                "channels": [
                    {
                        "channel_name": "ESPN2 USA",
                        "channel_id": "45"
                    }
                ]
            },
            {
                "time": "00:00",
                "event": "Street Outlaws: No Prep Kings Season 6, Episode 9",
                "channels": [
                    {
                        "channel_name": "Discovery USA",
                        "channel_id": "313"
                    }
                ]
            },
            {
                "time": "01:00",
                "event": "DMV Season 1, Episode 8",
                "channels": [
                    {
                        "channel_name": "CBSNY USA",
                        "channel_id": "767"
                    }
                ]
            },
            {
                "time": "01:00",
                "event": "Ridiculousness Season 48, Episode 28",
                "channels": [
                    {
                        "channel_name": "MTV USA",
                        "channel_id": "371"
                    }
                ]
            },
            {
                "time": "01:00",
                "event": "Finding Mr. Christmas Season 2, Episode 6",
                "channels": [
                    {
                        "channel_name": "The Hallmark Channel",
                        "channel_id": "320"
                    }
                ]
            },
            {
                "time": "01:00",
                "event": "Mysteries of the Unknown Season 9, Episode 44",
                "channels": [
                    {
                        "channel_name": "Travel Channel",
                        "channel_id": "340"
                    }
                ]
            },
            {
                "time": "01:00",
                "event": "Holiday Baking Championship Season 12, Episode 5",
                "channels": [
                    {
                        "channel_name": "The Food Network",
                        "channel_id": "384"
                    }
                ]
            },
            {
                "time": "01:00",
                "event": "The Wonderful World of Disney: Holiday Spectacular New",
                "channels": [
                    {
                        "channel_name": "ABC NY USA",
                        "channel_id": "766"
                    }
                ]
            },
            {
                "time": "01:00",
                "event": "Name That Tune Season 5, Episode 10",
                "channels": [
                    {
                        "channel_name": "FOXNY USA",
                        "channel_id": "768"
                    }
                ]
            },
            {
                "time": "01:00",
                "event": "St. Denis Medical Season 2, Episode 6",
                "channels": [
                    {
                        "channel_name": "NBCNY USA",
                        "channel_id": "769"
                    }
                ]
            },
            {
                "time": "01:00",
                "event": "Below Deck Mediterranean Season 10, Episode 10",
                "channels": [
                    {
                        "channel_name": "Bravo USA",
                        "channel_id": "307"
                    }
                ]
            },
            {
                "time": "01:00",
                "event": "90 Day Fianc\u00e9: The Other Way Season 7, Episode 13",
                "channels": [
                    {
                        "channel_name": "TLC USA",
                        "channel_id": "337"
                    }
                ]
            },
            {
                "time": "01:00",
                "event": "Love & Hip Hop Miami Season 7, Episode 4",
                "channels": [
                    {
                        "channel_name": "VH1 USA",
                        "channel_id": "344"
                    }
                ]
            },
            {
                "time": "01:00",
                "event": "MeatEater Season 13, Episode 7",
                "channels": [
                    {
                        "channel_name": "Outdoor Channel",
                        "channel_id": "848"
                    }
                ]
            },
            {
                "time": "01:00",
                "event": "World Chase Tag New",
                "channels": [
                    {
                        "channel_name": "NBCS Bay Area",
                        "channel_id": "753"
                    }
                ]
            },
            {
                "time": "01:30",
                "event": "The Neighborhood Season 8, Episode 7",
                "channels": [
                    {
                        "channel_name": "CBSNY USA",
                        "channel_id": "767"
                    }
                ]
            },
            {
                "time": "01:30",
                "event": "The Paper Season 1, Episode 4",
                "channels": [
                    {
                        "channel_name": "NBCNY USA",
                        "channel_id": "769"
                    }
                ]
            },
            {
                "time": "02:00",
                "event": "The Voice Season 28, Episode 15",
                "channels": [
                    {
                        "channel_name": "NBCNY USA",
                        "channel_id": "769"
                    }
                ]
            },
            {
                "time": "02:00",
                "event": "The Weakest Link Season 1, Episode 10",
                "channels": [
                    {
                        "channel_name": "FOXNY USA",
                        "channel_id": "768"
                    }
                ]
            },
            {
                "time": "02:00",
                "event": "TV We Love Season 1, Episode 8",
                "channels": [
                    {
                        "channel_name": "CW USA",
                        "channel_id": "300"
                    },
                    {
                        "channel_name": "CW PIX 11 USA",
                        "channel_id": "280"
                    }
                ]
            },
            {
                "time": "02:00",
                "event": "Gingerbread Land: The Biggest Little Holiday Competition Season 1, Episode 3",
                "channels": [
                    {
                        "channel_name": "Magnolia Network",
                        "channel_id": "299"
                    },
                    {
                        "channel_name": "The Food Network",
                        "channel_id": "384"
                    }
                ]
            },
            {
                "time": "02:00",
                "event": "Live PD: Greatest Shifts Season 1, Episode 22",
                "channels": [
                    {
                        "channel_name": "A&E TV USA",
                        "channel_id": "302"
                    }
                ]
            },
            {
                "time": "02:00",
                "event": "Rachael Ray's Meals in Minutes Season 3, Episode 33",
                "channels": [
                    {
                        "channel_name": "FYI USA",
                        "channel_id": "665"
                    }
                ]
            },
            {
                "time": "02:00",
                "event": "Ancient Aliens: Origins Season 2, Episode 8",
                "channels": [
                    {
                        "channel_name": "History USA",
                        "channel_id": "322"
                    }
                ]
            },
            {
                "time": "02:00",
                "event": "I Was a Teenage Felon Season 1",
                "channels": [
                    {
                        "channel_name": "VICE TV USA",
                        "channel_id": "659"
                    }
                ]
            },
            {
                "time": "02:00",
                "event": "Seeking Sister Wife Season 6, Episode 11",
                "channels": [
                    {
                        "channel_name": "TLC USA",
                        "channel_id": "337"
                    }
                ]
            },
            {
                "time": "02:00",
                "event": "Baked With Love: Holiday Season 1, Episode 6",
                "channels": [
                    {
                        "channel_name": "The Hallmark Channel",
                        "channel_id": "320"
                    }
                ]
            },
            {
                "time": "02:00",
                "event": "Fatal Attraction Season 16, Episode 17",
                "channels": [
                    {
                        "channel_name": "TV ONE USA",
                        "channel_id": "660"
                    }
                ]
            },
            {
                "time": "02:00",
                "event": "FBI Season 8, Episode 7",
                "channels": [
                    {
                        "channel_name": "CBSNY USA",
                        "channel_id": "767"
                    }
                ]
            },
            {
                "time": "03:00",
                "event": "Watson Season 2, Episode 8",
                "channels": [
                    {
                        "channel_name": "CBSNY USA",
                        "channel_id": "767"
                    }
                ]
            },
            {
                "time": "03:00",
                "event": "Brilliant Minds Season 2, Episode 10",
                "channels": [
                    {
                        "channel_name": "NBCNY USA",
                        "channel_id": "769"
                    }
                ]
            },
            {
                "time": "03:00",
                "event": "House Hunters Season 271, Episode 1",
                "channels": [
                    {
                        "channel_name": "HGTV USA",
                        "channel_id": "382"
                    }
                ]
            },
            {
                "time": "03:00",
                "event": "Cake Toppers Season 1, Episode 1 \u2022 Premiere",
                "channels": [
                    {
                        "channel_name": "FYI USA",
                        "channel_id": "665"
                    }
                ]
            },
            {
                "time": "04:30",
                "event": "Jimmy Kimmel Live! Season 24, Episode 41",
                "channels": [
                    {
                        "channel_name": "ABC NY USA",
                        "channel_id": "766"
                    }
                ]
            }
        ],
        "Socca World Championships": [
            {
                "time": "13:00",
                "event": "2025 Socca World Championships : Oman vs. Bulgaria",
                "channels": [
                    {
                        "channel_name": "NLSE",
                        "channel_id": "18"
                    }
                ]
            },
            {
                "time": "14:00",
                "event": "2025 Socca World Championships : Canada vs. Haiti",
                "channels": [
                    {
                        "channel_name": "NLSE",
                        "channel_id": "18"
                    }
                ]
            },
            {
                "time": "15:00",
                "event": "2025 Socca World Championships : Romania vs. England",
                "channels": [
                    {
                        "channel_name": "NLSE",
                        "channel_id": "18"
                    }
                ]
            },
            {
                "time": "22:00",
                "event": "2025 Socca World Championships : Greece vs. Serbia",
                "channels": [
                    {
                        "channel_name": "NLSE",
                        "channel_id": "18"
                    }
                ]
            },
            {
                "time": "23:00",
                "event": "2025 Socca World Championships : Hungary neutral Honduras",
                "channels": [
                    {
                        "channel_name": "NLSE",
                        "channel_id": "18"
                    }
                ]
            },
            {
                "time": "00:00",
                "event": "2025 Socca World Championships : Poland vs. Argentina",
                "channels": [
                    {
                        "channel_name": "NLSE",
                        "channel_id": "18"
                    }
                ]
            },
            {
                "time": "01:00",
                "event": "2025 Socca World Championships : Australia vs. Mexico",
                "channels": [
                    {
                        "channel_name": "NLSE",
                        "channel_id": "18"
                    }
                ]
            },
            {
                "time": "02:00",
                "event": "2025 Socca World Championships : Brazil neutral Morocco",
                "channels": [
                    {
                        "channel_name": "NLSE",
                        "channel_id": "18"
                    }
                ]
            },
            {
                "time": "03:00",
                "event": "2025 Socca World Championships : United States neutral Czechia",
                "channels": [
                    {
                        "channel_name": "NLSE",
                        "channel_id": "18"
                    }
                ]
            }
        ],
        "All Soccer Events": [
            {
                "time": "11:00",
                "event": "Women's Friendly : Ukraine vs Austria",
                "channels": [
                    {
                        "channel_name": "ORF Sport Plus",
                        "channel_id": "13"
                    }
                ]
            },
            {
                "time": "11:00",
                "event": "Portugal - Liga Revela\u00e7\u00e3o : Famalic\u00e3o U23 vs Vizela U23",
                "channels": [
                    {
                        "channel_name": "Canal 11 Portugal",
                        "channel_id": "540"
                    }
                ]
            },
            {
                "time": "11:30",
                "event": "Romania - Liga II : Sepsi vs CSMS Ia\u015fi",
                "channels": [
                    {
                        "channel_name": "Digi Sport 1 Romania",
                        "channel_id": "400"
                    },
                    {
                        "channel_name": "Prima Sport 1 Romania",
                        "channel_id": "583"
                    }
                ]
            },
            {
                "time": "13:00",
                "event": "World Arab Cup : Tunisia vs Syria",
                "channels": [
                    {
                        "channel_name": "beIN Sports MAX 5 France",
                        "channel_id": "495"
                    }
                ]
            },
            {
                "time": "14:00",
                "event": "Portugal - Segunda liga : Pa\u00e7os de Ferreira vs Felgueiras 1932",
                "channels": [
                    {
                        "channel_name": "Sport TV1 Portugal",
                        "channel_id": "49"
                    }
                ]
            },
            {
                "time": "14:00",
                "event": "Romania - Liga I : Petrolul 52 vs Metaloglobus",
                "channels": [
                    {
                        "channel_name": "Digi Sport 1 Romania",
                        "channel_id": "400"
                    },
                    {
                        "channel_name": "Prima Sport 1 Romania",
                        "channel_id": "583"
                    },
                    {
                        "channel_name": "Arena Sport 1 Croatia",
                        "channel_id": "432"
                    }
                ]
            },
            {
                "time": "15:00",
                "event": "Portugal - Liga Revela\u00e7\u00e3o : Torreense U23 vs Farense U23",
                "channels": [
                    {
                        "channel_name": "Canal 11 Portugal",
                        "channel_id": "540"
                    }
                ]
            },
            {
                "time": "15:30",
                "event": "Bulgaria - Second League : OFK Pirin vs Yantra",
                "channels": [
                    {
                        "channel_name": "Diema Sport Bulgaria",
                        "channel_id": "465"
                    },
                    {
                        "channel_name": "Sportklub 2 Croatia",
                        "channel_id": "102"
                    }
                ]
            },
            {
                "time": "15:45",
                "event": "World Arab Cup : Qatar vs Palestine",
                "channels": [
                    {
                        "channel_name": "beIN Sports MAX 5 France",
                        "channel_id": "495"
                    }
                ]
            },
            {
                "time": "16:00",
                "event": "Poland - I Liga : Stal Rzesz\u00f3w vs Pogo\u0144 Grod. Mazowiecki",
                "channels": [
                    {
                        "channel_name": "TVP Sport Poland",
                        "channel_id": "128"
                    }
                ]
            },
            {
                "time": "16:00",
                "event": "Portugal - Liga Revela\u00e7\u00e3o : Sporting CP U23 vs Estoril U23",
                "channels": [
                    {
                        "channel_name": "Sporting TV Portugal",
                        "channel_id": "716"
                    },
                    {
                        "channel_name": "Canal 11 Portugal",
                        "channel_id": "540"
                    }
                ]
            },
            {
                "time": "16:30",
                "event": "Russia - Russian Premier League : Sochi vs Dynamo Makhachkala",
                "channels": [
                    {
                        "channel_name": "Match Premier Russia",
                        "channel_id": "573"
                    },
                    {
                        "channel_name": "Arena 2 Premium Serbia",
                        "channel_id": "135"
                    },
                    {
                        "channel_name": "Arena Sport 2 Croatia",
                        "channel_id": "433"
                    }
                ]
            },
            {
                "time": "17:00",
                "event": "Turkey - 1. Lig : Adana Demirspor vs Hatayspor",
                "channels": [
                    {
                        "channel_name": "TRT Spor Turkey",
                        "channel_id": "889"
                    }
                ]
            },
            {
                "time": "17:00",
                "event": "Croatia - 1. HNL : Gorica vs Dinamo Zagreb",
                "channels": [
                    {
                        "channel_name": "MAX Sport 1 Croatia",
                        "channel_id": "779"
                    }
                ]
            },
            {
                "time": "17:00",
                "event": "Cyprus - First Division : Akritas vs AEK Larnaca",
                "channels": [
                    {
                        "channel_name": "Cytavision Sports 2 Cyprus",
                        "channel_id": "912"
                    }
                ]
            },
            {
                "time": "17:00",
                "event": "Cyprus - First Division : Omonia Nicosia vs Omonia Aradippou",
                "channels": [
                    {
                        "channel_name": "Cytavision Sports 1 Cyprus",
                        "channel_id": "911"
                    }
                ]
            },
            {
                "time": "17:00",
                "event": "Super Lig : Samsunspor vs Alanyaspor",
                "channels": [
                    {
                        "channel_name": "beIN Sports 2 Turkey",
                        "channel_id": "63"
                    }
                ]
            },
            {
                "time": "17:00",
                "event": "Super Lig : Fenerbah\u00e7e vs Galatasaray",
                "channels": [
                    {
                        "channel_name": "beIN Sports 1 Turkey",
                        "channel_id": "62"
                    },
                    {
                        "channel_name": "beIN SPORTS USA",
                        "channel_id": "425"
                    },
                    {
                        "channel_name": "beIN SPORTS en Espa\u00f1ol",
                        "channel_id": "372"
                    },
                    {
                        "channel_name": "Sport TV1 Portugal",
                        "channel_id": "49"
                    },
                    {
                        "channel_name": "beIN Sports 2 France",
                        "channel_id": "117"
                    },
                    {
                        "channel_name": "MATCH! Futbol 3 Russia",
                        "channel_id": "138"
                    },
                    {
                        "channel_name": "ESPN Mexico",
                        "channel_id": "925"
                    },
                    {
                        "channel_name": "Arena 1 Premium Serbia",
                        "channel_id": "134"
                    },
                    {
                        "channel_name": "ESPN4 Brazil",
                        "channel_id": "85"
                    },
                    {
                        "channel_name": "Sportklub 1 Croatia",
                        "channel_id": "101"
                    },
                    {
                        "channel_name": "beIN Sports MENA 2",
                        "channel_id": "92"
                    },
                    {
                        "channel_name": "Sport 1 Israel",
                        "channel_id": "140"
                    }
                ]
            },
            {
                "time": "17:00",
                "event": "Women's Friendly : Denmark vs Norway",
                "channels": [
                    {
                        "channel_name": "DR 2 Denmark",
                        "channel_id": "802"
                    }
                ]
            },
            {
                "time": "17:00",
                "event": "Israel - Liga Leumit : Bnei Yehuda vs Hapoel Nazareth Illit",
                "channels": [
                    {
                        "channel_name": "5 PLUS Israel",
                        "channel_id": "145"
                    }
                ]
            },
            {
                "time": "17:00",
                "event": "Israel - Liga Leumit : Hapoel Hadera vs Hapoel Kfar Shalem",
                "channels": [
                    {
                        "channel_name": "5 LIVE Israel",
                        "channel_id": "146"
                    }
                ]
            },
            {
                "time": "17:00",
                "event": "Israel - Liga Leumit : Maccabi Kabilio Jaffa vs Maccabi Herzliya",
                "channels": [
                    {
                        "channel_name": "5 STARS Israel",
                        "channel_id": "147"
                    }
                ]
            },
            {
                "time": "17:00",
                "event": "Romania - Liga I : Universitatea Cluj vs CSU Craiova",
                "channels": [
                    {
                        "channel_name": "Digi Sport 1 Romania",
                        "channel_id": "400"
                    },
                    {
                        "channel_name": "Prima Sport 1 Romania",
                        "channel_id": "583"
                    },
                    {
                        "channel_name": "Arena Sport 1 Croatia",
                        "channel_id": "432"
                    }
                ]
            },
            {
                "time": "17:15",
                "event": "Women's Friendly : Germany U23 W vs France U23 W",
                "channels": [
                    {
                        "channel_name": "DF1 DE",
                        "channel_id": "1"
                    }
                ]
            },
            {
                "time": "18:00",
                "event": "Denmark - Super Liga : Br\u00f8ndby vs Fredericia",
                "channels": [
                    {
                        "channel_name": "TV2 Sport X Denmark",
                        "channel_id": "808"
                    },
                    {
                        "channel_name": "Sportklub 3 Croatia",
                        "channel_id": "103"
                    }
                ]
            },
            {
                "time": "18:00",
                "event": "Poland - Ekstraklasa : Motor Lublin vs Legia Warszawa",
                "channels": [
                    {
                        "channel_name": "Canal+ Sport 3 Poland",
                        "channel_id": "259"
                    }
                ]
            },
            {
                "time": "18:00",
                "event": "Portugal - Segunda liga : Vizela vs Feirense",
                "channels": [
                    {
                        "channel_name": "Sport TV+ Portugal",
                        "channel_id": "2"
                    }
                ]
            },
            {
                "time": "19:00",
                "event": "Netherlands - Eerste Divisie : PSV II vs RKC Waalwijk",
                "channels": [
                    {
                        "channel_name": "ESPN 1 NL",
                        "channel_id": "379"
                    }
                ]
            },
            {
                "time": "19:00",
                "event": "Netherlands - Eerste Divisie : Ajax II vs Vitesse",
                "channels": [
                    {
                        "channel_name": "ESPN 2 NL",
                        "channel_id": "386"
                    }
                ]
            },
            {
                "time": "19:00",
                "event": "Portugal - Liga 3 : Sporting Braga II vs Trofense",
                "channels": [
                    {
                        "channel_name": "Canal 11 Portugal",
                        "channel_id": "540"
                    }
                ]
            },
            {
                "time": "19:30",
                "event": "Italy - Serie C : Vis Pesaro vs Ascoli",
                "channels": [
                    {
                        "channel_name": "Sky Sport 253 IT",
                        "channel_id": "3"
                    },
                    {
                        "channel_name": "Sky Sport Arena IT",
                        "channel_id": "462"
                    }
                ]
            },
            {
                "time": "19:30",
                "event": "Italy - Serie C : Benevento vs Salernitana",
                "channels": [
                    {
                        "channel_name": "Sky Sport 251 IT",
                        "channel_id": "4"
                    },
                    {
                        "channel_name": "Sky Sport Uno IT",
                        "channel_id": "461"
                    }
                ]
            },
            {
                "time": "19:30",
                "event": "Italy - Serie C : Cittadella vs Union Brescia",
                "channels": [
                    {
                        "channel_name": "Sky Sport 252 IT",
                        "channel_id": "5"
                    },
                    {
                        "channel_name": "Sky Sport Calcio IT",
                        "channel_id": "870"
                    }
                ]
            },
            {
                "time": "19:45",
                "event": "Italy - Serie A : Bologna vs Cremonese",
                "channels": [
                    {
                        "channel_name": "DAZN Zona IT",
                        "channel_id": "877"
                    },
                    {
                        "channel_name": "DAZN2 DE",
                        "channel_id": "427"
                    },
                    {
                        "channel_name": "Sport TV2 Portugal",
                        "channel_id": "74"
                    },
                    {
                        "channel_name": "Eleven Sports 1 Poland",
                        "channel_id": "71"
                    },
                    {
                        "channel_name": "Ziggo Sport 3 NL",
                        "channel_id": "919"
                    },
                    {
                        "channel_name": "Match! Football 1 Russia",
                        "channel_id": "136"
                    },
                    {
                        "channel_name": "Digi Sport 3 Romania",
                        "channel_id": "402"
                    },
                    {
                        "channel_name": "Arena 2 Premium Serbia",
                        "channel_id": "135"
                    },
                    {
                        "channel_name": "Cosmote Sport 2 Greece",
                        "channel_id": "623"
                    },
                    {
                        "channel_name": "Arena Sport 3 Croatia",
                        "channel_id": "434"
                    },
                    {
                        "channel_name": "TV4 Sport Live 1",
                        "channel_id": "703"
                    },
                    {
                        "channel_name": "MAX Sport 3 Bulgaria",
                        "channel_id": "474"
                    },
                    {
                        "channel_name": "ESPN3 Argentina",
                        "channel_id": "798"
                    },
                    {
                        "channel_name": "SuperSport Football",
                        "channel_id": "56"
                    },
                    {
                        "channel_name": "Sport 1 Israel",
                        "channel_id": "140"
                    }
                ]
            },
            {
                "time": "20:00",
                "event": "Spain - La Liga : Rayo Vallecano vs Valencia",
                "channels": [
                    {
                        "channel_name": "M+ LALIGA TV",
                        "channel_id": "84"
                    },
                    {
                        "channel_name": "LaLiga TV UK",
                        "channel_id": "276"
                    },
                    {
                        "channel_name": "Viaplay Sports 1 UK",
                        "channel_id": "451"
                    },
                    {
                        "channel_name": "Premier Sports 1 Ireland",
                        "channel_id": "771"
                    },
                    {
                        "channel_name": "DAZN1 DE",
                        "channel_id": "426"
                    },
                    {
                        "channel_name": "DAZN Eleven 1 Portugal",
                        "channel_id": "455"
                    },
                    {
                        "channel_name": "Eleven Sports 2 Poland",
                        "channel_id": "72"
                    },
                    {
                        "channel_name": "beIN Sports 1 France",
                        "channel_id": "116"
                    },
                    {
                        "channel_name": "Ziggo Sport 2 NL",
                        "channel_id": "398"
                    },
                    {
                        "channel_name": "ESPN Deportes",
                        "channel_id": "375"
                    },
                    {
                        "channel_name": "Digi Sport 2 Romania",
                        "channel_id": "401"
                    },
                    {
                        "channel_name": "Prima Sport 2 Romania",
                        "channel_id": "584"
                    },
                    {
                        "channel_name": "beIN Sports Malaysia",
                        "channel_id": "712"
                    },
                    {
                        "channel_name": "Arena 1 Premium Serbia",
                        "channel_id": "134"
                    },
                    {
                        "channel_name": "Nova Sports 1 Greece",
                        "channel_id": "631"
                    },
                    {
                        "channel_name": "Match! Football 2 Russia",
                        "channel_id": "137"
                    },
                    {
                        "channel_name": "Arena Sport 1 Croatia",
                        "channel_id": "432"
                    },
                    {
                        "channel_name": "TV4 Fotball",
                        "channel_id": "747"
                    },
                    {
                        "channel_name": "MAX Sport 4 Bulgaria",
                        "channel_id": "475"
                    },
                    {
                        "channel_name": "ESPN4 Brazil",
                        "channel_id": "85"
                    },
                    {
                        "channel_name": "ESPN2 Argentina",
                        "channel_id": "150"
                    },
                    {
                        "channel_name": "SuperSport Laliga",
                        "channel_id": "415"
                    },
                    {
                        "channel_name": "SuperSport MaXimo 1",
                        "channel_id": "572"
                    },
                    {
                        "channel_name": "beIN Sports MENA 3",
                        "channel_id": "93"
                    },
                    {
                        "channel_name": "beIN Sports MENA English 2",
                        "channel_id": "90"
                    }
                ]
            },
            {
                "time": "20:00",
                "event": "England - Championship : Birmingham City vs Watford",
                "channels": [
                    {
                        "channel_name": "CBS Sports Golazo USA",
                        "channel_id": "910"
                    },
                    {
                        "channel_name": "Sky Sports Football UK",
                        "channel_id": "35"
                    },
                    {
                        "channel_name": "Sky Sports Main Event UK",
                        "channel_id": "38"
                    },
                    {
                        "channel_name": "Sky Sport Premier League DE",
                        "channel_id": "6"
                    },
                    {
                        "channel_name": "Sky Sport Top Event DE",
                        "channel_id": "556"
                    },
                    {
                        "channel_name": "Sport TV3 Portugal",
                        "channel_id": "454"
                    },
                    {
                        "channel_name": "beIN Sports MAX 4 France",
                        "channel_id": "494"
                    },
                    {
                        "channel_name": "Arena 3 Premium Serbia",
                        "channel_id": "139"
                    },
                    {
                        "channel_name": "ESPN2 Mexico",
                        "channel_id": "926"
                    },
                    {
                        "channel_name": "Astro Football",
                        "channel_id": "124"
                    },
                    {
                        "channel_name": "Cosmote Sport 1 Greece",
                        "channel_id": "622"
                    },
                    {
                        "channel_name": "Diema Sport 2 Bulgaria",
                        "channel_id": "466"
                    },
                    {
                        "channel_name": "ESPN2 Brazil",
                        "channel_id": "82"
                    },
                    {
                        "channel_name": "beIN Sports MENA 2",
                        "channel_id": "92"
                    },
                    {
                        "channel_name": "beIN Sports MENA English 1",
                        "channel_id": "61"
                    },
                    {
                        "channel_name": "Sport 2 Israel",
                        "channel_id": "141"
                    }
                ]
            },
            {
                "time": "20:00",
                "event": "Argentina Primera Divisi\u00f3n : Barracas Central vs Gimnasia La Plata",
                "channels": [
                    {
                        "channel_name": "ESPN Premium Argentina",
                        "channel_id": "387"
                    }
                ]
            },
            {
                "time": "20:15",
                "event": "Portugal - Primeira Liga : Arouca vs Sporting Braga",
                "channels": [
                    {
                        "channel_name": "Sport TV1 Portugal",
                        "channel_id": "49"
                    },
                    {
                        "channel_name": "beIN Sports 2 France",
                        "channel_id": "117"
                    },
                    {
                        "channel_name": "Sportdigital FUSSBALL DE",
                        "channel_id": "571"
                    },
                    {
                        "channel_name": "Cosmote Sport 3 Greece",
                        "channel_id": "624"
                    },
                    {
                        "channel_name": "Ring bg",
                        "channel_id": "471"
                    },
                    {
                        "channel_name": "Sportklub 1 Croatia",
                        "channel_id": "101"
                    }
                ]
            },
            {
                "time": "23:00",
                "event": "CONCACAF W Championship : Barbados vs Trinidad and Tobago",
                "channels": [
                    {
                        "channel_name": "TUDN USA",
                        "channel_id": "66"
                    }
                ]
            },
            {
                "time": "23:00",
                "event": "Chile - Primera Division : Audax Italiano vs \u00d1ublense",
                "channels": [
                    {
                        "channel_name": "TNT SPORTS Premium Chile",
                        "channel_id": "642"
                    }
                ]
            },
            {
                "time": "00:00",
                "event": "Women's Friendly : USA vs Italy",
                "channels": [
                    {
                        "channel_name": "TBS USA",
                        "channel_id": "336"
                    },
                    {
                        "channel_name": "RAI 2 IT",
                        "channel_id": "851"
                    }
                ]
            },
            {
                "time": "01:00",
                "event": "Argentina Primera Divisi\u00f3n : Racing Club vs Tigre",
                "channels": [
                    {
                        "channel_name": "ESPN Premium Argentina",
                        "channel_id": "387"
                    },
                    {
                        "channel_name": "Viaplay Sports 2 UK",
                        "channel_id": "550"
                    },
                    {
                        "channel_name": "Sportdigital FUSSBALL DE",
                        "channel_id": "571"
                    },
                    {
                        "channel_name": "Sport TV2 Portugal",
                        "channel_id": "74"
                    }
                ]
            },
            {
                "time": "01:00",
                "event": "Colombia - Primera A : Medell\u00edn vs Am\u00e9rica de Cali",
                "channels": [
                    {
                        "channel_name": "Win+ Futbol Colombia",
                        "channel_id": "392"
                    }
                ]
            },
            {
                "time": "01:00",
                "event": "CONCACAF W Championship : Guatemala vs Bermuda",
                "channels": [
                    {
                        "channel_name": "TUDN USA",
                        "channel_id": "66"
                    }
                ]
            }
        ],
        "Cricket": [
            {
                "time": "08:10",
                "event": "Big Bash League Women : Hobart W vs Melbourne Stars W",
                "channels": [
                    {
                        "channel_name": "Willow Cricket",
                        "channel_id": "346"
                    },
                    {
                        "channel_name": "Sky Sports Cricket UK",
                        "channel_id": "65"
                    },
                    {
                        "channel_name": "Astro Cricket",
                        "channel_id": "370"
                    },
                    {
                        "channel_name": "Sky Sport 1 NZ",
                        "channel_id": "588"
                    },
                    {
                        "channel_name": "Sky Sports Main Event",
                        "channel_id": "38"
                    },
                    {
                        "channel_name": "SuperSport Cricket",
                        "channel_id": "368"
                    },
                    {
                        "channel_name": "SuperSport Grandstand",
                        "channel_id": "412"
                    }
                ]
            },
            {
                "time": "21:30",
                "event": "1st Test | Day 1 : New Zealand vs West Indies",
                "channels": [
                    {
                        "channel_name": "TNT Sports 2 UK",
                        "channel_id": "32"
                    },
                    {
                        "channel_name": "TNT Sports 1 UK",
                        "channel_id": "31"
                    },
                    {
                        "channel_name": "SuperSport Cricket",
                        "channel_id": "368"
                    },
                    {
                        "channel_name": "SuperSport Grandstand",
                        "channel_id": "412"
                    }
                ]
            },
            {
                "time": "23:00",
                "event": "Marsh One-Day Cup : Victorian Bushrangers vs Western Australia",
                "channels": [
                    {
                        "channel_name": "Sky Sport 2 NZ",
                        "channel_id": "589"
                    }
                ]
            }
        ],
        "Tennis": [
            {
                "time": "18:00",
                "event": "Mixed Coverage Center Court Live",
                "channels": [
                    {
                        "channel_name": "Tennis Channel",
                        "channel_id": "40"
                    }
                ]
            },
            {
                "time": "02:00",
                "event": "Mixed Coverage Center Court Live",
                "channels": [
                    {
                        "channel_name": "Tennis Channel",
                        "channel_id": "40"
                    }
                ]
            }
        ],
        "WWE (RAW)": [
            {
                "time": "00:00",
                "event": "WWE Monday Night RAW",
                "channels": [
                    {
                        "channel_name": "Netflix PPV",
                        "channel_id": "2"
                    },
                    {
                        "channel_name": "SuperSport Variety 4",
                        "channel_id": "419"
                    },
                    {
                        "channel_name": "SuperSport Grandstand",
                        "channel_id": "412"
                    },
                    {
                        "channel_name": "Supersports Action",
                        "channel_id": "420"
                    }
                ]
            }
        ],
        "Table Tennis": [
            {
                "time": "11:00",
                "event": "ITTF Mixed Team World Cup Chengdu 2025 First Phase",
                "channels": [
                    {
                        "channel_name": "SporTV2 Brazil",
                        "channel_id": "79"
                    }
                ]
            }
        ],
        "Snooker": [
            {
                "time": "13:00",
                "event": "UK Championship | Round 1",
                "channels": [
                    {
                        "channel_name": "TNT Sports 1 UK",
                        "channel_id": "31"
                    },
                    {
                        "channel_name": "EuroSport 1 Poland",
                        "channel_id": "57"
                    },
                    {
                        "channel_name": "EuroSport 1 Spain",
                        "channel_id": "524"
                    },
                    {
                        "channel_name": "EuroSport 1 France",
                        "channel_id": "772"
                    },
                    {
                        "channel_name": "Eurosport 1 SE",
                        "channel_id": "231"
                    },
                    {
                        "channel_name": "EuroSport 1 Italy",
                        "channel_id": "878"
                    },
                    {
                        "channel_name": "EuroSport 1 Greece",
                        "channel_id": "41"
                    }
                ]
            },
            {
                "time": "18:00",
                "event": "Ultimate Pool Mixed Pairs Cup | Week 5",
                "channels": [
                    {
                        "channel_name": "TNT Sports 2 UK",
                        "channel_id": "32"
                    },
                    {
                        "channel_name": "Sky Sport 1 NZ",
                        "channel_id": "588"
                    }
                ]
            },
            {
                "time": "18:45",
                "event": "UK Championship | Round 1",
                "channels": [
                    {
                        "channel_name": "TNT Sports 1 UK",
                        "channel_id": "31"
                    },
                    {
                        "channel_name": "EuroSport 1 Poland",
                        "channel_id": "57"
                    },
                    {
                        "channel_name": "EuroSport 1 Spain",
                        "channel_id": "524"
                    },
                    {
                        "channel_name": "EuroSport 1 France",
                        "channel_id": "772"
                    },
                    {
                        "channel_name": "Eurosport 1 SE",
                        "channel_id": "231"
                    },
                    {
                        "channel_name": "EuroSport 1 Italy",
                        "channel_id": "878"
                    },
                    {
                        "channel_name": "EuroSport 1 Greece",
                        "channel_id": "41"
                    }
                ]
            }
        ],
        "Am. Football (NFL)": [
            {
                "time": "01:15",
                "event": "NFL : New England Patriots vs New York Giants",
                "channels": [
                    {
                        "channel_name": "NFL Sunday Ticket",
                        "channel_id": "1"
                    },
                    {
                        "channel_name": "ESPN2 USA",
                        "channel_id": "45"
                    },
                    {
                        "channel_name": "ESPN USA",
                        "channel_id": "44"
                    },
                    {
                        "channel_name": "MY9TV USA",
                        "channel_id": "654"
                    },
                    {
                        "channel_name": "Sky Sports Main Event UK",
                        "channel_id": "38"
                    },
                    {
                        "channel_name": "Sky Sports NFL UK",
                        "channel_id": "37"
                    },
                    {
                        "channel_name": "TSN5",
                        "channel_id": "115"
                    },
                    {
                        "channel_name": "beIN Sports 2 France",
                        "channel_id": "117"
                    },
                    {
                        "channel_name": "RDS CA",
                        "channel_id": "839"
                    },
                    {
                        "channel_name": "ESPN 1 NL",
                        "channel_id": "379"
                    },
                    {
                        "channel_name": "TSN1",
                        "channel_id": "111"
                    },
                    {
                        "channel_name": "TSN3",
                        "channel_id": "113"
                    },
                    {
                        "channel_name": "ESPN Deportes",
                        "channel_id": "375"
                    },
                    {
                        "channel_name": "ESPN2 Mexico",
                        "channel_id": "926"
                    },
                    {
                        "channel_name": "Cosmote Sport 9 Greece",
                        "channel_id": "630"
                    },
                    {
                        "channel_name": "Arena 1 Premium Serbia",
                        "channel_id": "134"
                    },
                    {
                        "channel_name": "ESPN2 BR",
                        "channel_id": "82"
                    },
                    {
                        "channel_name": "ESPN2 Brazil",
                        "channel_id": "82"
                    },
                    {
                        "channel_name": "ESPN2 Argentina",
                        "channel_id": "150"
                    },
                    {
                        "channel_name": "5Sport Israel",
                        "channel_id": "144"
                    }
                ]
            }
        ],
        "Basketball": [
            {
                "time": "16:30",
                "event": "Elite League : AE Psychikoy vs Layrio",
                "channels": [
                    {
                        "channel_name": "ERT 2 Greece",
                        "channel_id": "7"
                    }
                ]
            },
            {
                "time": "16:30",
                "event": "Europe: World Cup - Qualification : Finland vs France",
                "channels": [
                    {
                        "channel_name": "beIN Sports 3 France",
                        "channel_id": "118"
                    }
                ]
            },
            {
                "time": "16:45",
                "event": "Europe: World Cup - Qualification : Cyprus vs Germany",
                "channels": [
                    {
                        "channel_name": "Magenta Sport 318",
                        "channel_id": "8"
                    }
                ]
            },
            {
                "time": "18:00",
                "event": "Europe: World Cup - Qualification : Sweden vs Slovenia",
                "channels": [
                    {
                        "channel_name": "Arena Premium 3 Serbia",
                        "channel_id": "139"
                    }
                ]
            },
            {
                "time": "18:30",
                "event": "Europe: World Cup - Qualification : Netherlands vs Poland",
                "channels": [
                    {
                        "channel_name": "TVP Sport Poland HD",
                        "channel_id": "128"
                    }
                ]
            },
            {
                "time": "19:00",
                "event": "Europe: World Cup - Qualification : Israel vs Croatia",
                "channels": [
                    {
                        "channel_name": "Arena Sport 3 Croatia",
                        "channel_id": "434"
                    },
                    {
                        "channel_name": "Arena Sport 4 Serbia",
                        "channel_id": "581"
                    },
                    {
                        "channel_name": "5Sport Israel",
                        "channel_id": "144"
                    }
                ]
            },
            {
                "time": "19:20",
                "event": "Europe: World Cup - Qualification : Austria vs Latvia",
                "channels": [
                    {
                        "channel_name": "ORF Sport Plus",
                        "channel_id": "13"
                    }
                ]
            },
            {
                "time": "19:30",
                "event": "Europe: World Cup - Qualification : Hungary vs Belgium",
                "channels": [
                    {
                        "channel_name": "Duna World Hungary",
                        "channel_id": "9"
                    }
                ]
            }
        ],
        "NCAA/NCAAW Basketball": [
            {
                "time": "23:00",
                "event": "NCAAW : Boston University vs Maine",
                "channels": [
                    {
                        "channel_name": "NESN USA",
                        "channel_id": "762"
                    }
                ]
            },
            {
                "time": "23:30",
                "event": "NCAA : Villanova vs Temple",
                "channels": [
                    {
                        "channel_name": "FOX Sports 1 USA",
                        "channel_id": "39"
                    }
                ]
            },
            {
                "time": "00:00",
                "event": "NCAA : Xavier vs St. Francis",
                "channels": [
                    {
                        "channel_name": "truTV USA",
                        "channel_id": "341"
                    }
                ]
            }
        ],
        "NBA": [
            {
                "time": "00:00",
                "event": "NBA : Detroit Pistons vs Atlanta Hawks",
                "channels": [
                    {
                        "channel_name": "NBA League Pass",
                        "channel_id": "2"
                    },
                    {
                        "channel_name": "Sportsnet East",
                        "channel_id": "408"
                    },
                    {
                        "channel_name": "Sportsnet West",
                        "channel_id": "407"
                    },
                    {
                        "channel_name": "FanDuel Sports Network Detroit",
                        "channel_id": "891"
                    }
                ]
            },
            {
                "time": "00:00",
                "event": "NBA : Indiana Pacers vs Cleveland Cavaliers",
                "channels": [
                    {
                        "channel_name": "NBA League Pass",
                        "channel_id": "3"
                    },
                    {
                        "channel_name": "TSN4",
                        "channel_id": "114"
                    },
                    {
                        "channel_name": "FanDuel Sports Network Indiana",
                        "channel_id": "894"
                    },
                    {
                        "channel_name": "FanDuel Sports Network Ohio",
                        "channel_id": "899"
                    }
                ]
            },
            {
                "time": "00:00",
                "event": "NBA : Washington Wizards vs Milwaukee Bucks",
                "channels": [
                    {
                        "channel_name": "NBA League Pass",
                        "channel_id": "4"
                    },
                    {
                        "channel_name": "Monumental Sports Network",
                        "channel_id": "778"
                    },
                    {
                        "channel_name": "FanDuel Sports Network Wisconsin",
                        "channel_id": "907"
                    },
                    {
                        "channel_name": "Cosmote Sport 4 Greece",
                        "channel_id": "625"
                    }
                ]
            },
            {
                "time": "00:30",
                "event": "NBA : Orlando Magic vs Chicago Bulls",
                "channels": [
                    {
                        "channel_name": "NBA League Pass",
                        "channel_id": "5"
                    },
                    {
                        "channel_name": "FanDuel Sports Network Florida",
                        "channel_id": "892"
                    },
                    {
                        "channel_name": "Sky Sport Top Event DE",
                        "channel_id": "556"
                    },
                    {
                        "channel_name": "beIN Sports 1 France",
                        "channel_id": "116"
                    },
                    {
                        "channel_name": "Diema Sport 2 Bulgaria",
                        "channel_id": "466"
                    },
                    {
                        "channel_name": "beIN SPORTS MENA 8",
                        "channel_id": "98"
                    },
                    {
                        "channel_name": "beIN SPORTS MENA English 1",
                        "channel_id": "61"
                    },
                    {
                        "channel_name": "ESPN4 Brazil",
                        "channel_id": "85"
                    }
                ]
            },
            {
                "time": "00:30",
                "event": "NBA : Brooklyn Nets vs Charlotte Hornets",
                "channels": [
                    {
                        "channel_name": "NBA League Pass",
                        "channel_id": "6"
                    },
                    {
                        "channel_name": "YES USA",
                        "channel_id": "763"
                    }
                ]
            },
            {
                "time": "00:30",
                "event": "NBA : Miami Heat vs Los Angeles Clippers",
                "channels": [
                    {
                        "channel_name": "NBA League Pass",
                        "channel_id": "7"
                    },
                    {
                        "channel_name": "Bally Sports Sun",
                        "channel_id": "905"
                    },
                    {
                        "channel_name": "FanDuel Sports Network SoCal",
                        "channel_id": "902"
                    }
                ]
            },
            {
                "time": "02:00",
                "event": "NBA : Utah Jazz vs Houston Rockets",
                "channels": [
                    {
                        "channel_name": "NBA League Pass",
                        "channel_id": "8"
                    },
                    {
                        "channel_name": "Space City Home Network",
                        "channel_id": "921"
                    }
                ]
            },
            {
                "time": "02:00",
                "event": "NBA : Denver Nuggets vs Dallas Mavericks",
                "channels": [
                    {
                        "channel_name": "NBA League Pass",
                        "channel_id": "9"
                    },
                    {
                        "channel_name": "Altitude USA",
                        "channel_id": "923"
                    },
                    {
                        "channel_name": "Sportsnet West",
                        "channel_id": "407"
                    },
                    {
                        "channel_name": "Sportsnet One",
                        "channel_id": "411"
                    },
                    {
                        "channel_name": "Sportsnet East",
                        "channel_id": "408"
                    },
                    {
                        "channel_name": "Sportsnet Ontario",
                        "channel_id": "406"
                    }
                ]
            },
            {
                "time": "03:00",
                "event": "NBA : Los Angeles Lakers vs Phoenix Suns",
                "channels": [
                    {
                        "channel_name": "NBA League Pass",
                        "channel_id": "10"
                    },
                    {
                        "channel_name": "Spectrum SportsNet USA",
                        "channel_id": "982"
                    },
                    {
                        "channel_name": "TSN4",
                        "channel_id": "114"
                    },
                    {
                        "channel_name": "Sky Sport Top Event DE",
                        "channel_id": "556"
                    },
                    {
                        "channel_name": "Sport TV1 Portugal",
                        "channel_id": "49"
                    },
                    {
                        "channel_name": "beIN Sports 1 France",
                        "channel_id": "116"
                    },
                    {
                        "channel_name": "Cosmote Sport 4 Greece",
                        "channel_id": "625"
                    },
                    {
                        "channel_name": "ESPN 2 NL",
                        "channel_id": "386"
                    },
                    {
                        "channel_name": "ESPN Mexico",
                        "channel_id": "925"
                    },
                    {
                        "channel_name": "Arena 2 Premium Serbia",
                        "channel_id": "135"
                    },
                    {
                        "channel_name": "ESPN4 Brazil",
                        "channel_id": "85"
                    },
                    {
                        "channel_name": "beIN SPORTS MENA English 1",
                        "channel_id": "61"
                    },
                    {
                        "channel_name": "beIN SPORTS MENA 8",
                        "channel_id": "98"
                    }
                ]
            }
        ],
        "Bowling": [
            {
                "time": "05:30",
                "event": "Ultimate Bowls Championship: E1",
                "channels": [
                    {
                        "channel_name": "Sky Sport Select NZ",
                        "channel_id": "587"
                    }
                ]
            }
        ],
        "Futsal": [
            {
                "time": "10:00",
                "event": "Women's Futsal: World Cup - Philippines 2025 quarter-final match",
                "channels": [
                    {
                        "channel_name": "TVP Sport Poland",
                        "channel_id": "128"
                    }
                ]
            },
            {
                "time": "12:30",
                "event": "Women's Futsal: World Cup - Philippines 2025 quarter-final match : Spain vs Morocco",
                "channels": [
                    {
                        "channel_name": "TVP Sport Poland",
                        "channel_id": "128"
                    },
                    {
                        "channel_name": "Teledeporte Spain (TDP)",
                        "channel_id": "529"
                    }
                ]
            },
            {
                "time": "16:00",
                "event": "Romania, Liga 1 : Luceafarul Buzau FC vs. Acs Mausoleul Marasesti",
                "channels": [
                    {
                        "channel_name": "Digi Sport 3 Romania",
                        "channel_id": "402"
                    }
                ]
            }
        ],
        "Handball": [
            {
                "time": "16:30",
                "event": "Serbia Super Liga : RK Crvena zvezda vs RK Metaloplastika Elixir",
                "channels": [
                    {
                        "channel_name": "Arena Sport 1 Serbia",
                        "channel_id": "429"
                    }
                ]
            },
            {
                "time": "16:30",
                "event": "Israel Division 1 : Maccabi Tel Aviv vs Hapoel Rishon Le Zion",
                "channels": [
                    {
                        "channel_name": "5Sport Israel",
                        "channel_id": "144"
                    }
                ]
            },
            {
                "time": "17:00",
                "event": "World Championship, Women : Czech Republic vs. Cuba",
                "channels": [
                    {
                        "channel_name": "CT Sport Czech HD",
                        "channel_id": "1033"
                    },
                    {
                        "channel_name": "TV2 Sport Denmark",
                        "channel_id": "810"
                    }
                ]
            },
            {
                "time": "17:00",
                "event": "World Championship, Women : Japan vs. Croatia",
                "channels": [
                    {
                        "channel_name": "Arena Sport 2 Serbia",
                        "channel_id": "430"
                    },
                    {
                        "channel_name": "M4 Sport Hungary",
                        "channel_id": "265"
                    },
                    {
                        "channel_name": "Teledeporte Spain (TDP)",
                        "channel_id": "529"
                    },
                    {
                        "channel_name": "Prima Sport 2 Romania",
                        "channel_id": "584"
                    },
                    {
                        "channel_name": "beIN Sports MAX 4 France",
                        "channel_id": "494"
                    }
                ]
            },
            {
                "time": "17:00",
                "event": "World Championship, Women : Republic of Korea vs. Kazakhstan",
                "channels": [
                    {
                        "channel_name": "TV3 Norge",
                        "channel_id": "10"
                    }
                ]
            },
            {
                "time": "19:30",
                "event": "World Championship, Women : Sweden vs. Brazil",
                "channels": [
                    {
                        "channel_name": "CT Sport Czech HD",
                        "channel_id": "1033"
                    },
                    {
                        "channel_name": "TV2 Sport Denmark",
                        "channel_id": "810"
                    }
                ]
            },
            {
                "time": "19:30",
                "event": "World Championship, Women : Denmark vs. Romania",
                "channels": [
                    {
                        "channel_name": "TV2 Denmark",
                        "channel_id": "817"
                    },
                    {
                        "channel_name": "Arena Sport 2 Serbia",
                        "channel_id": "430"
                    },
                    {
                        "channel_name": "Digi Sport 1 Romania",
                        "channel_id": "400"
                    }
                ]
            },
            {
                "time": "19:30",
                "event": "World Championship, Women : Hungary vs. Switzerland",
                "channels": [
                    {
                        "channel_name": "M4 Sport Hungary",
                        "channel_id": "265"
                    },
                    {
                        "channel_name": "SRF Zwei",
                        "channel_id": "11"
                    },
                    {
                        "channel_name": "Arena Sport 3 Serbia",
                        "channel_id": "431"
                    },
                    {
                        "channel_name": "beIN Sports 3 France",
                        "channel_id": "118"
                    }
                ]
            },
            {
                "time": "19:30",
                "event": "World Championship, Women : Norway vs. Angola",
                "channels": [
                    {
                        "channel_name": "TV3 Denmark",
                        "channel_id": "12"
                    },
                    {
                        "channel_name": "Teledeporte Spain (TDP)",
                        "channel_id": "529"
                    }
                ]
            }
        ],
        "Horse Racing": [
            {
                "time": "12:00",
                "event": "Live racing from around the UK",
                "channels": [
                    {
                        "channel_name": "Sky Sports Racing UK",
                        "channel_id": "554"
                    }
                ]
            },
            {
                "time": "12:00",
                "event": "Live racing from Kempton and Ayr",
                "channels": [
                    {
                        "channel_name": "Racing Tv UK",
                        "channel_id": "555"
                    }
                ]
            }
        ],
        "Ice Hockey": [
            {
                "time": "16:30",
                "event": "Russia KHL : Dynamo Moscow vs Torpedo Nizhny Novgorod",
                "channels": [
                    {
                        "channel_name": "Match TV Russia",
                        "channel_id": "127"
                    }
                ]
            },
            {
                "time": "17:30",
                "event": "Norway, Eliteserien : Vaalerenga IF Oslo vs. Narvik Ishockeyklubb",
                "channels": [
                    {
                        "channel_name": "TV2 Sport 2 Norway",
                        "channel_id": "14"
                    }
                ]
            }
        ],
        "NHL": [
            {
                "time": "00:00",
                "event": "NHL : Pittsburgh Penguins vs Philadelphia Flyers",
                "channels": [
                    {
                        "channel_name": "NHL Gamecenter",
                        "channel_id": "11"
                    },
                    {
                        "channel_name": "Viaplay Sports 2 UK",
                        "channel_id": "550"
                    },
                    {
                        "channel_name": "NHL Network",
                        "channel_id": "663"
                    },
                    {
                        "channel_name": "NBCS Philadelphia",
                        "channel_id": "777"
                    },
                    {
                        "channel_name": "TVA Sports",
                        "channel_id": "833"
                    },
                    {
                        "channel_name": "SportsNet Pittsburgh",
                        "channel_id": "922"
                    },
                    {
                        "channel_name": "TV3 Sport Denmark",
                        "channel_id": "809"
                    },
                    {
                        "channel_name": "Nova Sport 1 CZ",
                        "channel_id": "1021"
                    },
                    {
                        "channel_name": "V Sport Vinter",
                        "channel_id": "16"
                    }
                ]
            },
            {
                "time": "00:00",
                "event": "NHL : Columbus Blue Jackets vs New Jersey Devils",
                "channels": [
                    {
                        "channel_name": "NHL Gamecenter",
                        "channel_id": "12"
                    },
                    {
                        "channel_name": "MSG USA",
                        "channel_id": "765"
                    },
                    {
                        "channel_name": "FanDuel Sports Network Ohio",
                        "channel_id": "899"
                    },
                    {
                        "channel_name": "V Sport Premium",
                        "channel_id": "17"
                    }
                ]
            },
            {
                "time": "00:30",
                "event": "NHL : Winnipeg Jets vs Buffalo Sabres",
                "channels": [
                    {
                        "channel_name": "NHL Gamecenter",
                        "channel_id": "13"
                    }
                ]
            },
            {
                "time": "01:00",
                "event": "NHL : Anaheim Ducks vs St. Louis Blues",
                "channels": [
                    {
                        "channel_name": "NHL Gamecenter",
                        "channel_id": "14"
                    },
                    {
                        "channel_name": "FanDuel Sports Network Kansas City",
                        "channel_id": "895"
                    },
                    {
                        "channel_name": "FanDuel Sports Network Midwest",
                        "channel_id": "896"
                    }
                ]
            },
            {
                "time": "03:00",
                "event": "NHL : Utah Mammoth vs San Jose Sharks",
                "channels": [
                    {
                        "channel_name": "NHL Gamecenter",
                        "channel_id": "15"
                    },
                    {
                        "channel_name": "Viaplay Sports 1 UK",
                        "channel_id": "451"
                    },
                    {
                        "channel_name": "NBCS California",
                        "channel_id": "755"
                    },
                    {
                        "channel_name": "Sky Sport Mix DE",
                        "channel_id": "557"
                    },
                    {
                        "channel_name": "Nova Sport 1 CZ",
                        "channel_id": "1021"
                    },
                    {
                        "channel_name": "V Sport Vinter",
                        "channel_id": "16"
                    }
                ]
            }
        ],
        "Squash": [
            {
                "time": "23:00",
                "event": "Padel Tournament Final, Mexico 30.11",
                "channels": [
                    {
                        "channel_name": "Sport 2 Israel",
                        "channel_id": "141"
                    }
                ]
            }
        ],
        "Volleyball": [
            {
                "time": "15:00",
                "event": "Portugal, Liga A1 : GC Santo Tirso vs. SL Benfica",
                "channels": [
                    {
                        "channel_name": "Sport TV2 Portugal HD",
                        "channel_id": "74"
                    }
                ]
            },
            {
                "time": "16:30",
                "event": "PlusLiga : Jastrzebski Wegiel vs. KS Norwid Czestochowa",
                "channels": [
                    {
                        "channel_name": "Polsat Sport 1 Poland",
                        "channel_id": "47"
                    },
                    {
                        "channel_name": "Sportklub 4 Croatia",
                        "channel_id": "104"
                    }
                ]
            },
            {
                "time": "19:00",
                "event": "Orlen Liga Women : Chemik Police vs. Uni Opole",
                "channels": [
                    {
                        "channel_name": "Polsat Sport 1 Poland",
                        "channel_id": "47"
                    },
                    {
                        "channel_name": "Sportklub 2 Croatia",
                        "channel_id": "102"
                    }
                ]
            }
        ]
    }
}